ase2sprkkr/__init__.py
ase2sprkkr/version.py
ase2sprkkr/ase/__init__.py
ase2sprkkr/ase/build.py
ase2sprkkr/ase/pbc.py
ase2sprkkr/ase/symbols.py
ase2sprkkr/ase/visualise.py
ase2sprkkr/asr/__init__.py
ase2sprkkr/bindings/__init__.py
ase2sprkkr/bindings/es_finder.py
ase2sprkkr/bindings/spglib.py
ase2sprkkr/common/__init__.py
ase2sprkkr/common/alternative_types.py
ase2sprkkr/common/configuration.py
ase2sprkkr/common/configuration_containers.py
ase2sprkkr/common/configuration_definitions.py
ase2sprkkr/common/decorators.py
ase2sprkkr/common/directory.py
ase2sprkkr/common/doc.py
ase2sprkkr/common/formats.py
ase2sprkkr/common/generated_configuration_definitions.py
ase2sprkkr/common/grammar.py
ase2sprkkr/common/init_tests.py
ase2sprkkr/common/misc.py
ase2sprkkr/common/no_output.py
ase2sprkkr/common/options.py
ase2sprkkr/common/process_output_reader.py
ase2sprkkr/common/tools.py
ase2sprkkr/common/unique_values.py
ase2sprkkr/common/grammar_types/__init__.py
ase2sprkkr/common/grammar_types/arrays.py
ase2sprkkr/common/grammar_types/basic.py
ase2sprkkr/common/grammar_types/data.py
ase2sprkkr/common/grammar_types/grammar_type.py
ase2sprkkr/common/grammar_types/mixed.py
ase2sprkkr/common/grammar_types/warnings.py
ase2sprkkr/common/test/__init__.py
ase2sprkkr/common/test/init_tests.py
ase2sprkkr/common/test/test_common.py
ase2sprkkr/common/test/test_grammar_types.py
ase2sprkkr/input_parameters/__init__.py
ase2sprkkr/input_parameters/input_parameters.py
ase2sprkkr/input_parameters/input_parameters_definitions.py
ase2sprkkr/input_parameters/definitions/__init__.py
ase2sprkkr/input_parameters/definitions/arpes.py
ase2sprkkr/input_parameters/definitions/dos.py
ase2sprkkr/input_parameters/definitions/gilbert.py
ase2sprkkr/input_parameters/definitions/phagen.py
ase2sprkkr/input_parameters/definitions/scf.py
ase2sprkkr/input_parameters/definitions/sections.py
ase2sprkkr/input_parameters/test/__init__.py
ase2sprkkr/input_parameters/test/init_tests.py
ase2sprkkr-2.2.1.dist-info/LICENCE
ase2sprkkr-2.2.1.dist-info/METADATA
ase2sprkkr-2.2.1.dist-info/WHEEL
ase2sprkkr-2.2.1.dist-info/top_level.txt
ase2sprkkr-2.2.1.dist-info/RECORD
