Metadata-Version: 2.1
Name: ase2sprkkr
Version: 2.2.1
Summary: ASE (atomic simulation environment) interface to SPRKKR
Home-page: https://ase2sprkkr.github.io/ase2sprkkr/
Author: Matyáš Novák & Jano Minár
Author-email: ase2kkr@ntc.zcu.cz
Classifier: Programming Language :: Python :: 3
Classifier: License :: OSI Approved :: MIT License
Classifier: Operating System :: OS Independent
Requires-Python: >=3.7
License-File: LICENCE
Requires-Dist: ase
Requires-Dist: asr
Requires-Dist: spglib
Requires-Dist: pyparsing
Requires-Dist: mendeleev
Requires-Dist: platformdirs
Requires-Dist: packaging
